caracal/__init__.py
caracal/exceptions.py
caracal/logging_config.py
caracal/cli/__init__.py
caracal/cli/agent.py
caracal/cli/ledger.py
caracal/cli/main.py
caracal/cli/policy.py
caracal/cli/pricebook.py
caracal/config/__init__.py
caracal/config/settings.py
caracal/core/__init__.py
caracal/core/identity.py
caracal/core/ledger.py
caracal/core/metering.py
caracal/core/policy.py
caracal/core/pricebook.py
caracal/core/retry.py
caracal/sdk/__init__.py
caracal/sdk/client.py
caracal/sdk/context.py
caracal_core-0.1.0.dist-info/licenses/LICENSE
caracal_core-0.1.0.dist-info/METADATA
caracal_core-0.1.0.dist-info/WHEEL
caracal_core-0.1.0.dist-info/entry_points.txt
caracal_core-0.1.0.dist-info/top_level.txt
caracal_core-0.1.0.dist-info/RECORD
