Metadata-Version: 2.4
Name: caracal-core
Version: 0.1.0
Summary: Economic control plane for AI agents
Author: Caracal Contributors
License:                     GNU AFFERO GENERAL PUBLIC LICENSE
Project-URL: Homepage, https://github.com/Garudex-Labs/caracal
Project-URL: Documentation, https://github.com/Garudex-Labs/caracal/blob/main/README.md
Project-URL: Repository, https://github.com/Garudex-Labs/caracal
Project-URL: Issues, https://github.com/Garudex-Labs/caracal/issues
Keywords: ai,agents,economics,budgeting,metering,ledger,ase,spending,policy,enforcement
Classifier: Development Status :: 3 - Alpha
Classifier: Intended Audience :: Developers
Classifier: License :: OSI Approved :: GNU Affero General Public License v3
Classifier: Programming Language :: Python :: 3
Classifier: Programming Language :: Python :: 3.10
Classifier: Programming Language :: Python :: 3.11
Classifier: Programming Language :: Python :: 3.12
Classifier: Topic :: Software Development :: Libraries :: Python Modules
Classifier: Topic :: Office/Business :: Financial
Classifier: Topic :: System :: Monitoring
Requires-Python: >=3.10
License-File: LICENSE
Requires-Dist: click>=8.1.0
Requires-Dist: pyyaml>=6.0
Requires-Dist: hypothesis>=6.0.0
Requires-Dist: ase-protocol>=1.0.1
Provides-Extra: dev
Requires-Dist: pytest>=7.0.0; extra == "dev"
Requires-Dist: pytest-cov>=4.0.0; extra == "dev"
Requires-Dist: black>=23.0.0; extra == "dev"
Requires-Dist: ruff>=0.1.0; extra == "dev"
Requires-Dist: mypy>=1.0.0; extra == "dev"
Dynamic: license-file
